README.md
setup.py
easyTCP/__init__.py
easyTCP.egg-info/PKG-INFO
easyTCP.egg-info/SOURCES.txt
easyTCP.egg-info/dependency_links.txt
easyTCP.egg-info/requires.txt
easyTCP.egg-info/top_level.txt
easyTCP/CLIENT/backend/Client.py
easyTCP/CLIENT/backend/ClientExceptions.py
easyTCP/CLIENT/backend/Protocol.py
easyTCP/CLIENT/backend/__init__.py
easyTCP/CLIENT/utils/DEFAULT_ENCRYPTION.py
easyTCP/CLIENT/utils/DEFAULT_SETTINGS.py
easyTCP/CLIENT/utils/functions.py
easyTCP/SERVER/backend/Client.py
easyTCP/SERVER/backend/Protocol.py
easyTCP/SERVER/backend/__init__.py
easyTCP/SERVER/backend/server.py
easyTCP/SERVER/utils/BUILD_IN.py
easyTCP/SERVER/utils/DEFAULT_ENCRYPTION.py
easyTCP/SERVER/utils/DEFAULT_SETTINGS.py
easyTCP/SERVER/utils/__init__.py
easyTCP/SERVER/utils/decorators.py
easyTCP/SERVER/utils/functions.py