Metadata-Version: 1.2
Name: easyTCP
Version: 0.6.3
Summary: easy&fast way to create asyncronus server&clients
Home-page: https://github.com/dsal3389/easyTCP
Author: Daniel Sonbolian
Author-email: dsal3389@gmail.com
License: MIT
Download-URL: https://github.com/dsal3389/easyTCP.git
Platform: UNKNOWN
Classifier: Intended Audience :: Developers
Classifier: License :: OSI Approved :: MIT License
Classifier: Programming Language :: Python :: 3.5
Classifier: Programming Language :: Python :: 3.6
Classifier: Programming Language :: Python :: 3.7
Requires-Python: >=3.5.*
